jzd/__init__.py
jzd-1.0.2.dist-info/METADATA
jzd-1.0.2.dist-info/WHEEL
jzd-1.0.2.dist-info/top_level.txt
jzd-1.0.2.dist-info/RECORD
